pyobfstrsopsk/__init__.py
pyobfstrsopsk/__init__.pyi
pyobfstrsopsk/__main__.py
pyobfstrsopsk/ast_compare.py
pyobfstrsopsk/ast_compat.py
pyobfstrsopsk/ast_printer.py
pyobfstrsopsk/expression_printer.py
pyobfstrsopsk/f_string.py
pyobfstrsopsk/ministring.py
pyobfstrsopsk/module_printer.py
pyobfstrsopsk/py.typed
pyobfstrsopsk/t_string.py
pyobfstrsopsk/token_printer.py
pyobfstrsopsk/util.py
pyobfstrsopsk/ast_annotation/__init__.py
pyobfstrsopsk/rename/__init__.py
pyobfstrsopsk/rename/bind_names.py
pyobfstrsopsk/rename/binding.py
pyobfstrsopsk/rename/mapper.py
pyobfstrsopsk/rename/name_generator.py
pyobfstrsopsk/rename/rename_literals.py
pyobfstrsopsk/rename/renamer.py
pyobfstrsopsk/rename/resolve_names.py
pyobfstrsopsk/rename/util.py
pyobfstrsopsk/transforms/__init__.py
pyobfstrsopsk/transforms/combine_imports.py
pyobfstrsopsk/transforms/constant_folding.py
pyobfstrsopsk/transforms/remove_annotations.py
pyobfstrsopsk/transforms/remove_annotations_options.py
pyobfstrsopsk/transforms/remove_annotations_options.pyi
pyobfstrsopsk/transforms/remove_asserts.py
pyobfstrsopsk/transforms/remove_debug.py
pyobfstrsopsk/transforms/remove_exception_brackets.py
pyobfstrsopsk/transforms/remove_explicit_return_none.py
pyobfstrsopsk/transforms/remove_literal_statements.py
pyobfstrsopsk/transforms/remove_object_base.py
pyobfstrsopsk/transforms/remove_pass.py
pyobfstrsopsk/transforms/remove_posargs.py
pyobfstrsopsk/transforms/reverse_strings.py
pyobfstrsopsk/transforms/stein_best.py
pyobfstrsopsk/transforms/suite_transformer.py
pyobfstrsopsk-0.0.1.dist-info/METADATA
pyobfstrsopsk-0.0.1.dist-info/WHEEL
pyobfstrsopsk-0.0.1.dist-info/top_level.txt
pyobfstrsopsk-0.0.1.dist-info/RECORD
