Metadata-Version: 2.4
Name: pyobfstrsopsk
Version: 0.0.1
Summary: random python stuff
Author-email: rahull <devilsteinshorts@gmail.com>
License: MIT
Project-URL: Credits, https://t.me/rahull
Requires-Python: >=3.8
